TKT/__init__.py
TKT/DKT/DKT.py
TKT/DKT/__init__.py
TKT/DKT/Module/__init__.py
TKT/DKT/Module/configuration.py
TKT/DKT/Module/etl.py
TKT/DKT/Module/module.py
TKT/DKT/Module/run.py
TKT/DKT/Module/sym/__init__.py
TKT/DKT/Module/sym/fit_eval.py
TKT/DKT/Module/sym/net.py
TKT/shared/__init__.py
TKT/shared/etl.py
TKT/shared/parallel.py
TKT/shared/sym.py
TKT-0.0.1.dist-info/DESCRIPTION.rst
TKT-0.0.1.dist-info/METADATA
TKT-0.0.1.dist-info/RECORD
TKT-0.0.1.dist-info/WHEEL
TKT-0.0.1.dist-info/metadata.json
TKT-0.0.1.dist-info/top_level.txt
tests/__init__.py
tests/conftest.py
tests/test_dkt.py
tests/test_etl.py
