Metadata-Version: 2.0
Name: TKT
Version: 0.0.1
Summary: This project aims to provide multiple knowledge tracing models.
Home-page: UNKNOWN
Author: UNKNOWN
Author-email: UNKNOWN
License: UNKNOWN
Platform: UNKNOWN
Requires-Python: >=3.6
Requires-Dist: tqdm
Requires-Dist: mxnet
Requires-Dist: gluonnlp
Requires-Dist: sklearn
Requires-Dist: longling (>=1.3.2)
Provides-Extra: test
Requires-Dist: pytest (>=4); extra == 'test'
Requires-Dist: pytest-cov (>=2.6.0); extra == 'test'
Requires-Dist: pytest-pep8 (>=1); extra == 'test'
Requires-Dist: EduData (>=0.0.4); extra == 'test'
